Metadata-Version: 1.0
Name: inlinesas
Version: 0.1.3
Summary: Run SAS code from within a Python script.
Home-page: https://wrds-web.wharton.upenn.edu/wrds/
Author: Joe Dougherty
Author-email: josepd@wharton.upenn.edu
License: UNKNOWN
Keywords: SAS,etl
Platform: UNKNOWN
